hd2neo4j/__init__.py
hd2neo4j/mapping_config/__init__.py
hd2neo4j/mapping_config/mapping_config.py
hd2neo4j/neo4j/mapper.py
hd2neo4j/neo4j/repository.py
hd2neo4j/routes/mapper_routes.py
hd2neo4j/services.py
hd2neo4j/types/mapper_types.py
hd2neo4j/utils/__init__.py
hd2neo4j/utils/data_iterator.py
hd2neo4j/utils/utils.py
hd2neo4j/vectors/__init__.py
hd2neo4j/vectors/strategies/__init__.py
hd2neo4j/vectors/strategies/bag_of_words.py
hd2neo4j/vectors/strategies/sentence_transformer.py
hd2neo4j/vectors/vectorizer.py
hd2neo4j-0.1.8.dist-info/LICENSE
hd2neo4j-0.1.8.dist-info/METADATA
hd2neo4j-0.1.8.dist-info/WHEEL
hd2neo4j-0.1.8.dist-info/RECORD
